bot_alert_rate/__init__.py
bot_alert_rate/calculate_alert_rate.py
bot_alert_rate/constants.py
bot_alert_rate/local_alert_history.py
bot_alert_rate-0.0.5.dist-info/METADATA
bot_alert_rate-0.0.5.dist-info/WHEEL
bot_alert_rate-0.0.5.dist-info/top_level.txt
bot_alert_rate-0.0.5.dist-info/RECORD
